texttoaudio/__init__.py
texttoaudio/texttoaudio.py
texttoaudioconverter50-0.1.dist-info/METADATA
texttoaudioconverter50-0.1.dist-info/WHEEL
texttoaudioconverter50-0.1.dist-info/top_level.txt
texttoaudioconverter50-0.1.dist-info/RECORD
